vine_wayback.py
vine_wayback-0.0.6.dist-info/LICENSE
vine_wayback-0.0.6.dist-info/METADATA
vine_wayback-0.0.6.dist-info/WHEEL
vine_wayback-0.0.6.dist-info/entry_points.txt
vine_wayback-0.0.6.dist-info/top_level.txt
vine_wayback-0.0.6.dist-info/RECORD
