Metadata-Version: 2.2
Name: vine_wayback
Version: 0.0.6
Summary: Fetch Vines from the Wayback Machine
License: The MIT License (MIT)
Requires-Python: >=3.8
License-File: LICENSE
Requires-Dist: requests>=2.32.3
Requires-Dist: beautifulsoup4>=4.12.3
Requires-Dist: wayback>=0.4.5
